tox_ansible/__init__.py
tox_ansible/_version.py
tox_ansible/plugin.py
tox_ansible-25.11.1.dist-info/licenses/LICENSE
tox_ansible-25.11.1.dist-info/METADATA
tox_ansible-25.11.1.dist-info/WHEEL
tox_ansible-25.11.1.dist-info/entry_points.txt
tox_ansible-25.11.1.dist-info/top_level.txt
tox_ansible-25.11.1.dist-info/RECORD
