Metadata-Version: 2.4
Name: tox-ansible
Version: 25.11.1
Summary: A radical approach to testing ansible content
Author-email: "Bradley A. Thornton" <bthornto@redhat.com>
Maintainer-email: Ansible by Red Hat <info@ansible.com>
License-Expression: MIT
Project-URL: changelog, https://github.com/ansible/tox-ansible/releases
Project-URL: documentation, https://ansible.readthedocs.io/projects/tox-ansible/
Project-URL: homepage, https://github.com/ansible/tox-ansible
Project-URL: repository, https://github.com/ansible/tox-ansible
Keywords: ansible,collections,tox
Classifier: Development Status :: 5 - Production/Stable
Classifier: Intended Audience :: Developers
Classifier: Operating System :: OS Independent
Classifier: Topic :: Software Development :: Testing
Classifier: Topic :: Software Development :: Quality Assurance
Classifier: Topic :: Utilities
Classifier: Programming Language :: Python
Classifier: Programming Language :: Python :: 3
Classifier: Programming Language :: Python :: 3 :: Only
Classifier: Programming Language :: Python :: 3.10
Classifier: Programming Language :: Python :: 3.11
Classifier: Programming Language :: Python :: 3.12
Classifier: Programming Language :: Python :: 3.13
Classifier: Programming Language :: Python :: Implementation :: CPython
Classifier: Programming Language :: Python :: Implementation :: PyPy
Requires-Python: >=3.10
License-File: LICENSE
Requires-Dist: pytest>=8.4.1
Requires-Dist: pytest-ansible>=3.1.0
Requires-Dist: pytest-xdist>=3.8.0
Requires-Dist: pyyaml>=6.0.2
Requires-Dist: tox>=4.15.1
Dynamic: license-file
